kupicelib/__init__.py
kupicelib/client_server/__init__.py
kupicelib/client_server/sim_client.py
kupicelib/client_server/sim_server.py
kupicelib/client_server/srv_sim_runner.py
kupicelib/editor/__init__.py
kupicelib/editor/asc_editor.py
kupicelib/editor/asy_reader.py
kupicelib/editor/base_editor.py
kupicelib/editor/base_schematic.py
kupicelib/editor/ltspice_utils.py
kupicelib/editor/qsch_editor.py
kupicelib/editor/spice_editor.py
kupicelib/log/__init__.py
kupicelib/log/logfile_data.py
kupicelib/log/ltsteps.py
kupicelib/log/qspice_log_reader.py
kupicelib/log/semi_dev_op_reader.py
kupicelib/py.typed
kupicelib/raw/__init__.py
kupicelib/raw/raw_classes.py
kupicelib/raw/raw_convert.py
kupicelib/raw/raw_read.py
kupicelib/raw/raw_write.py
kupicelib/README.md
kupicelib/scripts/asc_to_qsch.py
kupicelib/scripts/asc_to_qsch_data.xml
kupicelib/scripts/histogram.py
kupicelib/scripts/ltsteps.py
kupicelib/scripts/rawplot.py
kupicelib/scripts/readme_update.py
kupicelib/scripts/run_server.py
kupicelib/sim/__init__.py
kupicelib/sim/process_callback.py
kupicelib/sim/run_task.py
kupicelib/sim/sim_runner.py
kupicelib/sim/sim_stepping.py
kupicelib/sim/simulator.py
kupicelib/sim/tookit/__init__.py
kupicelib/sim/tookit/failure_modes.py
kupicelib/sim/tookit/fast_worst_case.py
kupicelib/sim/tookit/montecarlo.py
kupicelib/sim/tookit/quick_sensitivity_analysis.py
kupicelib/sim/tookit/sim_analysis.py
kupicelib/sim/tookit/tolerance_deviations.py
kupicelib/sim/tookit/worst_case.py
kupicelib/simulators/__init__.py
kupicelib/simulators/ltspice_simulator.py
kupicelib/simulators/ngspice_simulator.py
kupicelib/simulators/qspice_simulator.py
kupicelib/simulators/xyce_simulator.py
kupicelib/utils/detect_encoding.py
kupicelib/utils/file_search.py
kupicelib/utils/sweep_iterators.py
kupicelib/utils/windows_short_names.py
kupicelib-1.0.1.dist-info/entry_points.txt
kupicelib-1.0.1.dist-info/LICENSE
kupicelib-1.0.1.dist-info/METADATA
kupicelib-1.0.1.dist-info/WHEEL
kupicelib-1.0.1.dist-info/RECORD
