Metadata-Version: 2.1
Name: kupicelib
Version: 1.0.1
Summary: A modified version of kupicelib for automating Spice simulations
License: GPL-3.0
Keywords: spice,ltspice,qspice,ngspice,electronic simulator,montecarlo,worst-case
Author: Ryota Kobayashi
Author-email: s.woods.m.29@gmail.com
Requires-Python: >=3.10,<4.0
Classifier: License :: OSI Approved :: GNU General Public License v3 (GPLv3)
Classifier: Programming Language :: Python :: 3
Classifier: Programming Language :: Python :: 3.10
Classifier: Programming Language :: Python :: 3.11
Classifier: Programming Language :: Python :: 3.12
Classifier: Programming Language :: Python :: 3.13
Requires-Dist: clipboard
Requires-Dist: keyboard
Requires-Dist: matplotlib
Requires-Dist: numpy
Requires-Dist: pandas (>=2.2.3,<3.0.0)
Requires-Dist: pandas-stubs (>=2.2.3.241126,<3.0.0.0)
Requires-Dist: psutil
Requires-Dist: scipy
Requires-Dist: types-keyboard (>=0.13.2.20240310,<0.14.0.0)
Requires-Dist: types-psutil (>=7.0.0.20250218,<8.0.0.0)
Project-URL: author, https://github.com/RK0429
Project-URL: bug-tracker, https://github.com/RK0429/kupicelib/issues
Project-URL: homepage, https://github.com/RK0429/kupicelib
Project-URL: repository, https://github.com/RK0429/kupicelib.git
